taskmind/__init__.py
taskmind/api.py
taskmind/core.py
taskmind/dsl.py
taskmind/explain.py
taskmind/utils.py
taskmind-0.1.0.dist-info/licenses/LICENSE
taskmind-0.1.0.dist-info/METADATA
taskmind-0.1.0.dist-info/WHEEL
taskmind-0.1.0.dist-info/top_level.txt
taskmind-0.1.0.dist-info/RECORD
