Metadata-Version: 2.4
Name: taskmind
Version: 0.1.0
Summary: An intelligent, explainable rules engine with DSL and REST API
Author-email: Chandupa Dilhana <your.email@example.com>
License: MIT License
Classifier: Programming Language :: Python :: 3
Classifier: License :: OSI Approved :: MIT License
Classifier: Operating System :: OS Independent
Requires-Python: >=3.9
License-File: LICENSE
Requires-Dist: fastapi
Requires-Dist: uvicorn
Dynamic: license-file
